{
  "protocol_version" : "0.0.6",
  "configuration" : {
    "version" : "(6.13.0) (explicit/2db7aa41)",
    "tlc" : "__thread",
    "sigsgev" : "normal",
    "notifications" : "kqueue",
    "architecture" : "arm64",
    "disabled_features" : "com,shared_perfcounters",
    "smallconfig" : "disabled",
    "bigarrays" : "disabled",
    "softdebug" : "enabled",
    "interpreter" : "enabled",
    "llvm_support" : "disabled",
    "suspend" : "preemptive"
  },
  "memory" : {
    "Resident Size" : "515702784",
    "Virtual Size" : "422253936640",
    "minor_gc_time" : "0",
    "major_gc_time" : "2153702",
    "minor_gc_count" : "0",
    "major_gc_count" : "15",
    "major_gc_time_concurrent" : "0"
 },
  "threads" : [
 {
    "is_managed" : true,
    "offset_free_hash" : "0x25930a1842",
    "offset_rich_hash" : "0x25930a2c30",
    "crashed" : true,
    "native_thread_id" : "0x1f0ae9e00",
    "thread_info_addr" : "0x1260f6000",
    "thread_name" : "tid_103",
    "ctx" : {
      "IP" : "0x30405bb90",
      "SP" : "0x16af36b50",
      "BP" : "0x16af38b10"
  },
    "managed_frames" : [
  {
      "is_managed" : "false",
      "native_address" : "unregistered"
   }
,
  {
      "is_managed" : "true",
      "guid" : "4E1980F7-52FB-4681-93FD-B6362A30E4CD",
      "token" : "0x00000",
      "native_offset" : "0x0",
      "filename" : "Unity.XR.OpenXR.dll",
      "sizeofimage" : "0x30000",
      "timestamp" : "0xe490deba",
      "il_offset" : "0xffffffff"
   }
,
  {
      "is_managed" : "true",
      "guid" : "4E1980F7-52FB-4681-93FD-B6362A30E4CD",
      "token" : "0x6000049",
      "native_offset" : "0x0",
      "filename" : "Unity.XR.OpenXR.dll",
      "sizeofimage" : "0x30000",
      "timestamp" : "0xe490deba",
      "il_offset" : "0x00055"
   }
,
  {
      "is_managed" : "true",
      "guid" : "6A9007DF-2490-4C27-BC0D-5500898FFF63",
      "token" : "0x600099e",
      "native_offset" : "0x0",
      "filename" : "UnityEngine.CoreModule.dll",
      "sizeofimage" : "0x17a000",
      "timestamp" : "0xee042ce9",
      "il_offset" : "0x00033"
   }
,
  {
      "is_managed" : "true",
      "guid" : "6A9007DF-2490-4C27-BC0D-5500898FFF63",
      "token" : "0x6000502",
      "native_offset" : "0x0",
      "filename" : "UnityEngine.CoreModule.dll",
      "sizeofimage" : "0x17a000",
      "timestamp" : "0xee042ce9",
      "il_offset" : "0x00001"
   }
,
  {
      "is_managed" : "true",
      "guid" : "8F2B770C-4A1B-401A-99BA-9ED80A5C09B9",
      "token" : "0x00000",
      "native_offset" : "0x0",
      "filename" : "mscorlib.dll",
      "sizeofimage" : "0x470000",
      "timestamp" : "0xa6d36809",
      "il_offset" : "0x0002a"
   }
,
  {
      "is_managed" : "false",
      "native_address" : "unregistered"
   }
,
  {
      "is_managed" : "true",
      "guid" : "96F369BA-F40B-463B-90DE-4A26B095A803",
      "token" : "0x00000",
      "native_offset" : "0x0",
      "filename" : "UnityEditor.CoreModule.dll",
      "sizeofimage" : "0x952000",
      "timestamp" : "0x972b352c",
      "il_offset" : "0xffffffff"
   }
,
  {
      "is_managed" : "true",
      "guid" : "96F369BA-F40B-463B-90DE-4A26B095A803",
      "token" : "0x6002c46",
      "native_offset" : "0x0",
      "filename" : "UnityEditor.CoreModule.dll",
      "sizeofimage" : "0x952000",
      "timestamp" : "0x972b352c",
      "il_offset" : "0x00000"
   }
,
  {
      "is_managed" : "true",
      "guid" : "96F369BA-F40B-463B-90DE-4A26B095A803",
      "token" : "0x6005adb",
      "native_offset" : "0x0",
      "filename" : "UnityEditor.CoreModule.dll",
      "sizeofimage" : "0x952000",
      "timestamp" : "0x972b352c",
      "il_offset" : "0x000ff"
   }
,
  {
      "is_managed" : "true",
      "guid" : "96F369BA-F40B-463B-90DE-4A26B095A803",
      "token" : "0x600331c",
      "native_offset" : "0x0",
      "filename" : "UnityEditor.CoreModule.dll",
      "sizeofimage" : "0x952000",
      "timestamp" : "0x972b352c",
      "il_offset" : "0x00330"
   }
,
  {
      "is_managed" : "true",
      "guid" : "96F369BA-F40B-463B-90DE-4A26B095A803",
      "token" : "0x6003e93",
      "native_offset" : "0x0",
      "filename" : "UnityEditor.CoreModule.dll",
      "sizeofimage" : "0x952000",
      "timestamp" : "0x972b352c",
      "il_offset" : "0x0005a"
   }
,
  {
      "is_managed" : "true",
      "guid" : "96F369BA-F40B-463B-90DE-4A26B095A803",
      "token" : "0x600364c",
      "native_offset" : "0x0",
      "filename" : "UnityEditor.CoreModule.dll",
      "sizeofimage" : "0x952000",
      "timestamp" : "0x972b352c",
      "il_offset" : "0x00001"
   }
,
  {
      "is_managed" : "true",
      "guid" : "96F369BA-F40B-463B-90DE-4A26B095A803",
      "token" : "0x600364b",
      "native_offset" : "0x0",
      "filename" : "UnityEditor.CoreModule.dll",
      "sizeofimage" : "0x952000",
      "timestamp" : "0x972b352c",
      "il_offset" : "0x0019a"
   }
,
  {
      "is_managed" : "true",
      "guid" : "E9884C55-B6B2-42F8-9594-A7989619167F",
      "token" : "0x600117f",
      "native_offset" : "0x0",
      "filename" : "UnityEngine.UIElementsModule.dll",
      "sizeofimage" : "0x17c000",
      "timestamp" : "0x968b4264",
      "il_offset" : "0x00232"
   }
,
  {
      "is_managed" : "true",
      "guid" : "E9884C55-B6B2-42F8-9594-A7989619167F",
      "token" : "0x600118c",
      "native_offset" : "0x0",
      "filename" : "UnityEngine.UIElementsModule.dll",
      "sizeofimage" : "0x17c000",
      "timestamp" : "0x968b4264",
      "il_offset" : "0x000c4"
   }
,
  {
      "is_managed" : "true",
      "guid" : "E9884C55-B6B2-42F8-9594-A7989619167F",
      "token" : "0x6001182",
      "native_offset" : "0x0",
      "filename" : "UnityEngine.UIElementsModule.dll",
      "sizeofimage" : "0x17c000",
      "timestamp" : "0x968b4264",
      "il_offset" : "0x00068"
   }
,
  {
      "is_managed" : "true",
      "guid" : "E9884C55-B6B2-42F8-9594-A7989619167F",
      "token" : "0x6002287",
      "native_offset" : "0x0",
      "filename" : "UnityEngine.UIElementsModule.dll",
      "sizeofimage" : "0x17c000",
      "timestamp" : "0x968b4264",
      "il_offset" : "0x000e9"
   }
,
  {
      "is_managed" : "true",
      "guid" : "E9884C55-B6B2-42F8-9594-A7989619167F",
      "token" : "0x6002249",
      "native_offset" : "0x0",
      "filename" : "UnityEngine.UIElementsModule.dll",
      "sizeofimage" : "0x17c000",
      "timestamp" : "0x968b4264",
      "il_offset" : "0x00574"
   }
,
  {
      "is_managed" : "true",
      "guid" : "E9884C55-B6B2-42F8-9594-A7989619167F",
      "token" : "0x60022e8",
      "native_offset" : "0x0",
      "filename" : "UnityEngine.UIElementsModule.dll",
      "sizeofimage" : "0x17c000",
      "timestamp" : "0x968b4264",
      "il_offset" : "0x000f0"
   }
,
  {
      "is_managed" : "true",
      "guid" : "E9884C55-B6B2-42F8-9594-A7989619167F",
      "token" : "0x6001420",
      "native_offset" : "0x0",
      "filename" : "UnityEngine.UIElementsModule.dll",
      "sizeofimage" : "0x17c000",
      "timestamp" : "0x968b4264",
      "il_offset" : "0x000c0"
   }
,
  {
      "is_managed" : "true",
      "guid" : "E9884C55-B6B2-42F8-9594-A7989619167F",
      "token" : "0x60021ad",
      "native_offset" : "0x0",
      "filename" : "UnityEngine.UIElementsModule.dll",
      "sizeofimage" : "0x17c000",
      "timestamp" : "0x968b4264",
      "il_offset" : "0x0001e"
   }
,
  {
      "is_managed" : "true",
      "guid" : "E9884C55-B6B2-42F8-9594-A7989619167F",
      "token" : "0x6001321",
      "native_offset" : "0x0",
      "filename" : "UnityEngine.UIElementsModule.dll",
      "sizeofimage" : "0x17c000",
      "timestamp" : "0x968b4264",
      "il_offset" : "0x00035"
   }
,
  {
      "is_managed" : "true",
      "guid" : "E9884C55-B6B2-42F8-9594-A7989619167F",
      "token" : "0x6001328",
      "native_offset" : "0x0",
      "filename" : "UnityEngine.UIElementsModule.dll",
      "sizeofimage" : "0x17c000",
      "timestamp" : "0x968b4264",
      "il_offset" : "0x00078"
   }
,
  {
      "is_managed" : "true",
      "guid" : "E9884C55-B6B2-42F8-9594-A7989619167F",
      "token" : "0x6001e81",
      "native_offset" : "0x0",
      "filename" : "UnityEngine.UIElementsModule.dll",
      "sizeofimage" : "0x17c000",
      "timestamp" : "0x968b4264",
      "il_offset" : "0x00051"
   }
,
  {
      "is_managed" : "true",
      "guid" : "E9884C55-B6B2-42F8-9594-A7989619167F",
      "token" : "0x6001e75",
      "native_offset" : "0x0",
      "filename" : "UnityEngine.UIElementsModule.dll",
      "sizeofimage" : "0x17c000",
      "timestamp" : "0x968b4264",
      "il_offset" : "0x0003d"
   }
,
  {
      "is_managed" : "true",
      "guid" : "E9884C55-B6B2-42F8-9594-A7989619167F",
      "token" : "0x6001e63",
      "native_offset" : "0x0",
      "filename" : "UnityEngine.UIElementsModule.dll",
      "sizeofimage" : "0x17c000",
      "timestamp" : "0x968b4264",
      "il_offset" : "0x0001a"
   }
,
  {
      "is_managed" : "true",
      "guid" : "E9884C55-B6B2-42F8-9594-A7989619167F",
      "token" : "0x6001e6c",
      "native_offset" : "0x0",
      "filename" : "UnityEngine.UIElementsModule.dll",
      "sizeofimage" : "0x17c000",
      "timestamp" : "0x968b4264",
      "il_offset" : "0x00001"
   }
,
  {
      "is_managed" : "true",
      "guid" : "9316890D-A0FB-45C3-9D1A-45324E84DDED",
      "token" : "0x60003cd",
      "native_offset" : "0x0",
      "filename" : "UnityEngine.IMGUIModule.dll",
      "sizeofimage" : "0x34000",
      "timestamp" : "0xc9942a8c",
      "il_offset" : "0x00010"
   }
,
  {
      "is_managed" : "true",
      "guid" : "9316890D-A0FB-45C3-9D1A-45324E84DDED",
      "token" : "0x00000",
      "native_offset" : "0x0",
      "filename" : "UnityEngine.IMGUIModule.dll",
      "sizeofimage" : "0x34000",
      "timestamp" : "0xc9942a8c",
      "il_offset" : "0x0002a"
   }

  ],
  "unmanaged_frames" : [
 {
    "is_managed" : "false",
    "native_address" : "0x298a055f8",
    "native_offset" : "0x00000"
  }
,
 {
    "is_managed" : "false",
    "native_address" : "0x298b3c6b8",
    "native_offset" : "0x00000"
  }
,
 {
    "is_managed" : "false",
    "native_address" : "0x298b3ca14",
    "native_offset" : "0x00000"
  }
,
 {
    "is_managed" : "false",
    "native_address" : "0x298b3d004",
    "native_offset" : "0x00000"
  }
,
 {
    "is_managed" : "false",
    "native_address" : "0x298a47458",
    "native_offset" : "0x00000"
  }
,
 {
    "is_managed" : "false",
    "native_address" : "0x298a09790",
    "native_offset" : "0x00000"
  }
,
 {
    "is_managed" : "false",
    "native_address" : "0x298991eb8",
    "native_offset" : "0x00000"
  }
,
 {
    "is_managed" : "false",
    "native_address" : "0x195b42a24",
    "native_offset" : "0x00000"
  }
,
 {
    "is_managed" : "false",
    "native_address" : "0x17e747d84",
    "native_offset" : "0x00000"
  }
,
 {
    "is_managed" : "false",
    "native_address" : "0x17e741a38",
    "native_offset" : "0x00000"
  }
,
 {
    "is_managed" : "false",
    "native_address" : "0x2c5303134",
    "native_offset" : "0x00000"
  }
,
 {
    "is_managed" : "false",
    "native_address" : "0x2c523b560",
    "native_offset" : "0x00000"
  }
,
 {
    "is_managed" : "false",
    "native_address" : "0x2c523b490",
    "native_offset" : "0x00000"
  }
,
 {
    "is_managed" : "false",
    "native_address" : "0x2c523b778",
    "native_offset" : "0x00000"
  }
,
 {
    "is_managed" : "true",
    "guid" : "4E1980F7-52FB-4681-93FD-B6362A30E4CD",
    "token" : "0x00000",
    "native_offset" : "0x0",
    "filename" : "Unity.XR.OpenXR.dll",
    "sizeofimage" : "0x30000",
    "timestamp" : "0xe490deba",
    "il_offset" : "0x00000"
  }
,
 {
    "is_managed" : "true",
    "guid" : "4E1980F7-52FB-4681-93FD-B6362A30E4CD",
    "token" : "0x6000049",
    "native_offset" : "0x0",
    "filename" : "Unity.XR.OpenXR.dll",
    "sizeofimage" : "0x30000",
    "timestamp" : "0xe490deba",
    "il_offset" : "0x00000"
  }
,
 {
    "is_managed" : "true",
    "guid" : "6A9007DF-2490-4C27-BC0D-5500898FFF63",
    "token" : "0x600099e",
    "native_offset" : "0x0",
    "filename" : "UnityEngine.CoreModule.dll",
    "sizeofimage" : "0x17a000",
    "timestamp" : "0xee042ce9",
    "il_offset" : "0x00000"
  }
,
 {
    "is_managed" : "true",
    "guid" : "6A9007DF-2490-4C27-BC0D-5500898FFF63",
    "token" : "0x6000502",
    "native_offset" : "0x0",
    "filename" : "UnityEngine.CoreModule.dll",
    "sizeofimage" : "0x17a000",
    "timestamp" : "0xee042ce9",
    "il_offset" : "0x00000"
  }
,
 {
    "is_managed" : "true",
    "guid" : "8F2B770C-4A1B-401A-99BA-9ED80A5C09B9",
    "token" : "0x00000",
    "native_offset" : "0x0",
    "filename" : "mscorlib.dll",
    "sizeofimage" : "0x470000",
    "timestamp" : "0xa6d36809",
    "il_offset" : "0x00000"
  }
,
 {
    "is_managed" : "false",
    "native_address" : "0x298995178",
    "native_offset" : "0x00000"
  }
,
 {
    "is_managed" : "false",
    "native_address" : "0x298b1b3ec",
    "native_offset" : "0x00000"
  }
,
 {
    "is_managed" : "false",
    "native_address" : "0x298b1b30c",
    "native_offset" : "0x00000"
  }
,
 {
    "is_managed" : "false",
    "native_address" : "0x105bcdf98",
    "native_offset" : "0x00000"
  }
,
 {
    "is_managed" : "false",
    "native_address" : "0x105ba9e98",
    "native_offset" : "0x00000"
  }
,
 {
    "is_managed" : "false",
    "native_address" : "0x105814cdc",
    "native_offset" : "0x00000"
  }
,
 {
    "is_managed" : "false",
    "native_address" : "0x106651f1c",
    "native_offset" : "0x00000"
  }
,
 {
    "is_managed" : "false",
    "native_address" : "0x106b4f19c",
    "native_offset" : "0x00000"
  }
,
 {
    "is_managed" : "false",
    "native_address" : "0x10526b000",
    "native_offset" : "0x00000"
  }
,
 {
    "is_managed" : "true",
    "guid" : "96F369BA-F40B-463B-90DE-4A26B095A803",
    "token" : "0x00000",
    "native_offset" : "0x0",
    "filename" : "UnityEditor.CoreModule.dll",
    "sizeofimage" : "0x952000",
    "timestamp" : "0x972b352c",
    "il_offset" : "0x00000"
  }
,
 {
    "is_managed" : "true",
    "guid" : "96F369BA-F40B-463B-90DE-4A26B095A803",
    "token" : "0x6002c46",
    "native_offset" : "0x0",
    "filename" : "UnityEditor.CoreModule.dll",
    "sizeofimage" : "0x952000",
    "timestamp" : "0x972b352c",
    "il_offset" : "0x00000"
  }
,
 {
    "is_managed" : "true",
    "guid" : "96F369BA-F40B-463B-90DE-4A26B095A803",
    "token" : "0x6005adb",
    "native_offset" : "0x0",
    "filename" : "UnityEditor.CoreModule.dll",
    "sizeofimage" : "0x952000",
    "timestamp" : "0x972b352c",
    "il_offset" : "0x00000"
  }
,
 {
    "is_managed" : "true",
    "guid" : "96F369BA-F40B-463B-90DE-4A26B095A803",
    "token" : "0x600331c",
    "native_offset" : "0x0",
    "filename" : "UnityEditor.CoreModule.dll",
    "sizeofimage" : "0x952000",
    "timestamp" : "0x972b352c",
    "il_offset" : "0x00000"
  }
,
 {
    "is_managed" : "true",
    "guid" : "96F369BA-F40B-463B-90DE-4A26B095A803",
    "token" : "0x6003e93",
    "native_offset" : "0x0",
    "filename" : "UnityEditor.CoreModule.dll",
    "sizeofimage" : "0x952000",
    "timestamp" : "0x972b352c",
    "il_offset" : "0x00000"
  }
,
 {
    "is_managed" : "true",
    "guid" : "96F369BA-F40B-463B-90DE-4A26B095A803",
    "token" : "0x600364c",
    "native_offset" : "0x0",
    "filename" : "UnityEditor.CoreModule.dll",
    "sizeofimage" : "0x952000",
    "timestamp" : "0x972b352c",
    "il_offset" : "0x00000"
  }
,
 {
    "is_managed" : "true",
    "guid" : "96F369BA-F40B-463B-90DE-4A26B095A803",
    "token" : "0x600364b",
    "native_offset" : "0x0",
    "filename" : "UnityEditor.CoreModule.dll",
    "sizeofimage" : "0x952000",
    "timestamp" : "0x972b352c",
    "il_offset" : "0x00000"
  }
,
 {
    "is_managed" : "true",
    "guid" : "E9884C55-B6B2-42F8-9594-A7989619167F",
    "token" : "0x600117f",
    "native_offset" : "0x0",
    "filename" : "UnityEngine.UIElementsModule.dll",
    "sizeofimage" : "0x17c000",
    "timestamp" : "0x968b4264",
    "il_offset" : "0x00000"
  }
,
 {
    "is_managed" : "true",
    "guid" : "E9884C55-B6B2-42F8-9594-A7989619167F",
    "token" : "0x600118c",
    "native_offset" : "0x0",
    "filename" : "UnityEngine.UIElementsModule.dll",
    "sizeofimage" : "0x17c000",
    "timestamp" : "0x968b4264",
    "il_offset" : "0x00000"
  }
,
 {
    "is_managed" : "true",
    "guid" : "E9884C55-B6B2-42F8-9594-A7989619167F",
    "token" : "0x6001182",
    "native_offset" : "0x0",
    "filename" : "UnityEngine.UIElementsModule.dll",
    "sizeofimage" : "0x17c000",
    "timestamp" : "0x968b4264",
    "il_offset" : "0x00000"
  }
,
 {
    "is_managed" : "true",
    "guid" : "E9884C55-B6B2-42F8-9594-A7989619167F",
    "token" : "0x6002287",
    "native_offset" : "0x0",
    "filename" : "UnityEngine.UIElementsModule.dll",
    "sizeofimage" : "0x17c000",
    "timestamp" : "0x968b4264",
    "il_offset" : "0x00000"
  }
,
 {
    "is_managed" : "true",
    "guid" : "E9884C55-B6B2-42F8-9594-A7989619167F",
    "token" : "0x6002249",
    "native_offset" : "0x0",
    "filename" : "UnityEngine.UIElementsModule.dll",
    "sizeofimage" : "0x17c000",
    "timestamp" : "0x968b4264",
    "il_offset" : "0x00000"
  }
,
 {
    "is_managed" : "true",
    "guid" : "E9884C55-B6B2-42F8-9594-A7989619167F",
    "token" : "0x60022e8",
    "native_offset" : "0x0",
    "filename" : "UnityEngine.UIElementsModule.dll",
    "sizeofimage" : "0x17c000",
    "timestamp" : "0x968b4264",
    "il_offset" : "0x00000"
  }
,
 {
    "is_managed" : "true",
    "guid" : "E9884C55-B6B2-42F8-9594-A7989619167F",
    "token" : "0x6001420",
    "native_offset" : "0x0",
    "filename" : "UnityEngine.UIElementsModule.dll",
    "sizeofimage" : "0x17c000",
    "timestamp" : "0x968b4264",
    "il_offset" : "0x00000"
  }
,
 {
    "is_managed" : "true",
    "guid" : "E9884C55-B6B2-42F8-9594-A7989619167F",
    "token" : "0x60021ad",
    "native_offset" : "0x0",
    "filename" : "UnityEngine.UIElementsModule.dll",
    "sizeofimage" : "0x17c000",
    "timestamp" : "0x968b4264",
    "il_offset" : "0x00000"
  }
,
 {
    "is_managed" : "true",
    "guid" : "E9884C55-B6B2-42F8-9594-A7989619167F",
    "token" : "0x6001321",
    "native_offset" : "0x0",
    "filename" : "UnityEngine.UIElementsModule.dll",
    "sizeofimage" : "0x17c000",
    "timestamp" : "0x968b4264",
    "il_offset" : "0x00000"
  }
,
 {
    "is_managed" : "true",
    "guid" : "E9884C55-B6B2-42F8-9594-A7989619167F",
    "token" : "0x6001328",
    "native_offset" : "0x0",
    "filename" : "UnityEngine.UIElementsModule.dll",
    "sizeofimage" : "0x17c000",
    "timestamp" : "0x968b4264",
    "il_offset" : "0x00000"
  }
,
 {
    "is_managed" : "true",
    "guid" : "E9884C55-B6B2-42F8-9594-A7989619167F",
    "token" : "0x6001e81",
    "native_offset" : "0x0",
    "filename" : "UnityEngine.UIElementsModule.dll",
    "sizeofimage" : "0x17c000",
    "timestamp" : "0x968b4264",
    "il_offset" : "0x00000"
  }
,
 {
    "is_managed" : "true",
    "guid" : "E9884C55-B6B2-42F8-9594-A7989619167F",
    "token" : "0x6001e75",
    "native_offset" : "0x0",
    "filename" : "UnityEngine.UIElementsModule.dll",
    "sizeofimage" : "0x17c000",
    "timestamp" : "0x968b4264",
    "il_offset" : "0x00000"
  }
,
 {
    "is_managed" : "true",
    "guid" : "E9884C55-B6B2-42F8-9594-A7989619167F",
    "token" : "0x6001e63",
    "native_offset" : "0x0",
    "filename" : "UnityEngine.UIElementsModule.dll",
    "sizeofimage" : "0x17c000",
    "timestamp" : "0x968b4264",
    "il_offset" : "0x00000"
  }
,
 {
    "is_managed" : "true",
    "guid" : "E9884C55-B6B2-42F8-9594-A7989619167F",
    "token" : "0x6001e6c",
    "native_offset" : "0x0",
    "filename" : "UnityEngine.UIElementsModule.dll",
    "sizeofimage" : "0x17c000",
    "timestamp" : "0x968b4264",
    "il_offset" : "0x00000"
  }
,
 {
    "is_managed" : "true",
    "guid" : "9316890D-A0FB-45C3-9D1A-45324E84DDED",
    "token" : "0x60003cd",
    "native_offset" : "0x0",
    "filename" : "UnityEngine.IMGUIModule.dll",
    "sizeofimage" : "0x34000",
    "timestamp" : "0xc9942a8c",
    "il_offset" : "0x00000"
  }
,
 {
    "is_managed" : "true",
    "guid" : "9316890D-A0FB-45C3-9D1A-45324E84DDED",
    "token" : "0x00000",
    "native_offset" : "0x0",
    "filename" : "UnityEngine.IMGUIModule.dll",
    "sizeofimage" : "0x34000",
    "timestamp" : "0xc9942a8c",
    "il_offset" : "0x00000"
  }
,
 {
    "is_managed" : "false",
    "native_address" : "0x298995178",
    "native_offset" : "0x00000"
  }
,
 {
    "is_managed" : "false",
    "native_address" : "0x298b1b3ec",
    "native_offset" : "0x00000"
  }
,
 {
    "is_managed" : "false",
    "native_address" : "0x298b1b30c",
    "native_offset" : "0x00000"
  }
,
 {
    "is_managed" : "false",
    "native_address" : "0x105bcdf98",
    "native_offset" : "0x00000"
  }
,
 {
    "is_managed" : "false",
    "native_address" : "0x105ba9e98",
    "native_offset" : "0x00000"
  }
,
 {
    "is_managed" : "false",
    "native_address" : "0x105cfadc0",
    "native_offset" : "0x00000"
  }
,
 {
    "is_managed" : "false",
    "native_address" : "0x1065f7200",
    "native_offset" : "0x00000"
  }
,
 {
    "is_managed" : "false",
    "native_address" : "0x1079e39c4",
    "native_offset" : "0x00000"
  }
,
 {
    "is_managed" : "false",
    "native_address" : "0x1065f6634",
    "native_offset" : "0x00000"
  }
,
 {
    "is_managed" : "false",
    "native_address" : "0x1079f2b4c",
    "native_offset" : "0x00000"
  }
,
 {
    "is_managed" : "false",
    "native_address" : "0x1079f057c",
    "native_offset" : "0x00000"
  }
,
 {
    "is_managed" : "false",
    "native_address" : "0x1079e5358",
    "native_offset" : "0x00000"
  }
,
 {
    "is_managed" : "false",
    "native_address" : "0x1079e55d4",
    "native_offset" : "0x00000"
  }
,
 {
    "is_managed" : "false",
    "native_address" : "0x10675758c",
    "native_offset" : "0x00000"
  }
,
 {
    "is_managed" : "false",
    "native_address" : "0x10674fce8",
    "native_offset" : "0x00000"
  }
,
 {
    "is_managed" : "false",
    "native_address" : "0x10674d23c",
    "native_offset" : "0x00000"
  }
,
 {
    "is_managed" : "false",
    "native_address" : "0x1079d0de0",
    "native_offset" : "0x00000"
  }
,
 {
    "is_managed" : "false",
    "native_address" : "0x196ba2448",
    "native_offset" : "0x00000"
  }
,
 {
    "is_managed" : "false",
    "native_address" : "0x195c0c3c8",
    "native_offset" : "0x00000"
  }
,
 {
    "is_managed" : "false",
    "native_address" : "0x195c0c070",
    "native_offset" : "0x00000"
  }
,
 {
    "is_managed" : "false",
    "native_address" : "0x195c0bbc8",
    "native_offset" : "0x00000"
  }
,
 {
    "is_managed" : "false",
    "native_address" : "0x195bf1348",
    "native_offset" : "0x00000"
  }
,
 {
    "is_managed" : "false",
    "native_address" : "0x195bf04b8",
    "native_offset" : "0x00000"
  }
,
 {
    "is_managed" : "false",
    "native_address" : "0x19f43ac40",
    "native_offset" : "0x00000"
  }
,
 {
    "is_managed" : "false",
    "native_address" : "0x19f43a8d0",
    "native_offset" : "0x00000"
  }
,
 {
    "is_managed" : "false",
    "native_address" : "0x19f43a7d4",
    "native_offset" : "0x00000"
  }
,
 {
    "is_managed" : "false",
    "native_address" : "0x198e11d44",
    "native_offset" : "0x00000"
  }
,
 {
    "is_managed" : "false",
    "native_address" : "0x198e10ee0",
    "native_offset" : "0x00000"
  }
,
 {
    "is_managed" : "false",
    "native_address" : "0x198e05344",
    "native_offset" : "0x00000"
  }

 ]
},
{
  "is_managed" : false,
  "offset_free_hash" : "0x0",
  "offset_rich_hash" : "0x0",
  "crashed" : false,
  "native_thread_id" : "0x17badf000",
  "thread_info_addr" : "0x29d2fb600",
  "thread_name" : "tid_da0b",
  "ctx" : {
    "IP" : "0x195ad3e90",
    "SP" : "0x17baded10",
    "BP" : "0x17baded20"
 },
  "unmanaged_frames" : [
 {
    "is_managed" : "false",
    "native_address" : "0x298a055f8",
    "native_offset" : "0x00000"
  }
,
 {
    "is_managed" : "false",
    "native_address" : "0x298b3c6b8",
    "native_offset" : "0x00000"
  }
,
 {
    "is_managed" : "false",
    "native_address" : "0x298b3ca14",
    "native_offset" : "0x00000"
  }
,
 {
    "is_managed" : "false",
    "native_address" : "0x298b3c7dc",
    "native_offset" : "0x00000"
  }
,
 {
    "is_managed" : "false",
    "native_address" : "0x298a4660c",
    "native_offset" : "0x00000"
  }
,
 {
    "is_managed" : "false",
    "native_address" : "0x195b42a24",
    "native_offset" : "0x00000"
  }
,
 {
    "is_managed" : "false",
    "native_address" : "0x19596499c",
    "native_offset" : "0x00000"
  }
,
 {
    "is_managed" : "false",
    "native_address" : "0x195965050",
    "native_offset" : "0x00000"
  }
,
 {
    "is_managed" : "false",
    "native_address" : "0x107a902a4",
    "native_offset" : "0x00000"
  }
,
 {
    "is_managed" : "false",
    "native_address" : "0x1057a0d58",
    "native_offset" : "0x00000"
  }
,
 {
    "is_managed" : "false",
    "native_address" : "0x1057a1f3c",
    "native_offset" : "0x00000"
  }
,
 {
    "is_managed" : "false",
    "native_address" : "0x105a017d8",
    "native_offset" : "0x00000"
  }
,
 {
    "is_managed" : "false",
    "native_address" : "0x195b13fa8",
    "native_offset" : "0x00000"
  }
,
 {
    "is_managed" : "false",
    "native_address" : "0x195b0eda0",
    "native_offset" : "0x00000"
  }

 ]
},
{
  "is_managed" : false,
  "offset_free_hash" : "0x0",
  "offset_rich_hash" : "0x0",
  "crashed" : false,
  "native_thread_id" : "0x298767000",
  "thread_info_addr" : "0x12613ba00",
  "thread_name" : "Finalizer",
  "ctx" : {
    "IP" : "0x195ad3e90",
    "SP" : "0x298766dd0",
    "BP" : "0x298766e50"
 },
  "unmanaged_frames" : [
 {
    "is_managed" : "false",
    "native_address" : "0x298a055f8",
    "native_offset" : "0x00000"
  }
,
 {
    "is_managed" : "false",
    "native_address" : "0x298b3c6b8",
    "native_offset" : "0x00000"
  }
,
 {
    "is_managed" : "false",
    "native_address" : "0x298b3ca14",
    "native_offset" : "0x00000"
  }
,
 {
    "is_managed" : "false",
    "native_address" : "0x298b3c7dc",
    "native_offset" : "0x00000"
  }
,
 {
    "is_managed" : "false",
    "native_address" : "0x298a4660c",
    "native_offset" : "0x00000"
  }
,
 {
    "is_managed" : "false",
    "native_address" : "0x195b42a24",
    "native_offset" : "0x00000"
  }
,
 {
    "is_managed" : "false",
    "native_address" : "0x298b7626c",
    "native_offset" : "0x00000"
  }
,
 {
    "is_managed" : "false",
    "native_address" : "0x298b3d424",
    "native_offset" : "0x00000"
  }
,
 {
    "is_managed" : "false",
    "native_address" : "0x298b3d2d0",
    "native_offset" : "0x00000"
  }
,
 {
    "is_managed" : "false",
    "native_address" : "0x298bbcd18",
    "native_offset" : "0x00000"
  }
,
 {
    "is_managed" : "false",
    "native_address" : "0x298bbcca0",
    "native_offset" : "0x00000"
  }
,
 {
    "is_managed" : "false",
    "native_address" : "0x195b13fa8",
    "native_offset" : "0x00000"
  }
,
 {
    "is_managed" : "false",
    "native_address" : "0x195b0eda0",
    "native_offset" : "0x00000"
  }

 ]
},
{
  "is_managed" : false,
  "offset_free_hash" : "0x0",
  "offset_rich_hash" : "0x0",
  "crashed" : false,
  "native_thread_id" : "0x17d1eb000",
  "thread_info_addr" : "0x1262f1200",
  "thread_name" : "tid_10503",
  "ctx" : {
    "IP" : "0x195ad3e90",
    "SP" : "0x17d1ead10",
    "BP" : "0x17d1ead20"
 },
  "unmanaged_frames" : [
 {
    "is_managed" : "false",
    "native_address" : "0x298a055f8",
    "native_offset" : "0x00000"
  }
,
 {
    "is_managed" : "false",
    "native_address" : "0x298b3c6b8",
    "native_offset" : "0x00000"
  }
,
 {
    "is_managed" : "false",
    "native_address" : "0x298b3ca14",
    "native_offset" : "0x00000"
  }
,
 {
    "is_managed" : "false",
    "native_address" : "0x298b3c7dc",
    "native_offset" : "0x00000"
  }
,
 {
    "is_managed" : "false",
    "native_address" : "0x298a4660c",
    "native_offset" : "0x00000"
  }
,
 {
    "is_managed" : "false",
    "native_address" : "0x195b42a24",
    "native_offset" : "0x00000"
  }
,
 {
    "is_managed" : "false",
    "native_address" : "0x19596499c",
    "native_offset" : "0x00000"
  }
,
 {
    "is_managed" : "false",
    "native_address" : "0x195965050",
    "native_offset" : "0x00000"
  }
,
 {
    "is_managed" : "false",
    "native_address" : "0x107a902a4",
    "native_offset" : "0x00000"
  }
,
 {
    "is_managed" : "false",
    "native_address" : "0x1057a0d58",
    "native_offset" : "0x00000"
  }
,
 {
    "is_managed" : "false",
    "native_address" : "0x1057a1f3c",
    "native_offset" : "0x00000"
  }
,
 {
    "is_managed" : "false",
    "native_address" : "0x105a017d8",
    "native_offset" : "0x00000"
  }
,
 {
    "is_managed" : "false",
    "native_address" : "0x195b13fa8",
    "native_offset" : "0x00000"
  }
,
 {
    "is_managed" : "false",
    "native_address" : "0x195b0eda0",
    "native_offset" : "0x00000"
  }

 ]
},
{
  "is_managed" : false,
  "offset_free_hash" : "0x0",
  "offset_rich_hash" : "0x0",
  "crashed" : false,
  "native_thread_id" : "0x2a161f000",
  "thread_info_addr" : "0x1243dd000",
  "thread_name" : "Thread Pool I/O Selector",
  "ctx" : {
    "IP" : "0x195adeff0",
    "SP" : "0x2a161eae0",
    "BP" : "0x2a161ece0"
 },
  "unmanaged_frames" : [
 {
    "is_managed" : "false",
    "native_address" : "0x298a055f8",
    "native_offset" : "0x00000"
  }
,
 {
    "is_managed" : "false",
    "native_address" : "0x298b3c6b8",
    "native_offset" : "0x00000"
  }
,
 {
    "is_managed" : "false",
    "native_address" : "0x298b3ca14",
    "native_offset" : "0x00000"
  }
,
 {
    "is_managed" : "false",
    "native_address" : "0x298b3c7dc",
    "native_offset" : "0x00000"
  }
,
 {
    "is_managed" : "false",
    "native_address" : "0x298a4660c",
    "native_offset" : "0x00000"
  }
,
 {
    "is_managed" : "false",
    "native_address" : "0x195b42a24",
    "native_offset" : "0x00000"
  }
,
 {
    "is_managed" : "false",
    "native_address" : "0x298b8e910",
    "native_offset" : "0x00000"
  }
,
 {
    "is_managed" : "false",
    "native_address" : "0x298b41bf4",
    "native_offset" : "0x00000"
  }
,
 {
    "is_managed" : "false",
    "native_address" : "0x298b4160c",
    "native_offset" : "0x00000"
  }
,
 {
    "is_managed" : "false",
    "native_address" : "0x298b3d424",
    "native_offset" : "0x00000"
  }
,
 {
    "is_managed" : "false",
    "native_address" : "0x298b3d2d0",
    "native_offset" : "0x00000"
  }
,
 {
    "is_managed" : "false",
    "native_address" : "0x298bbcd18",
    "native_offset" : "0x00000"
  }
,
 {
    "is_managed" : "false",
    "native_address" : "0x298bbcca0",
    "native_offset" : "0x00000"
  }
,
 {
    "is_managed" : "false",
    "native_address" : "0x195b13fa8",
    "native_offset" : "0x00000"
  }
,
 {
    "is_managed" : "false",
    "native_address" : "0x195b0eda0",
    "native_offset" : "0x00000"
  }

 ]
},
{
  "is_managed" : false,
  "offset_free_hash" : "0x0",
  "offset_rich_hash" : "0x0",
  "crashed" : false,
  "native_thread_id" : "0x17d303000",
  "thread_info_addr" : "0x126061600",
  "thread_name" : "tid_10903",
  "ctx" : {
    "IP" : "0x195ad3e90",
    "SP" : "0x17d302d10",
    "BP" : "0x17d302d20"
 },
  "unmanaged_frames" : [
 {
    "is_managed" : "false",
    "native_address" : "0x298a055f8",
    "native_offset" : "0x00000"
  }
,
 {
    "is_managed" : "false",
    "native_address" : "0x298b3c6b8",
    "native_offset" : "0x00000"
  }
,
 {
    "is_managed" : "false",
    "native_address" : "0x298b3ca14",
    "native_offset" : "0x00000"
  }
,
 {
    "is_managed" : "false",
    "native_address" : "0x298b3c7dc",
    "native_offset" : "0x00000"
  }
,
 {
    "is_managed" : "false",
    "native_address" : "0x298a4660c",
    "native_offset" : "0x00000"
  }
,
 {
    "is_managed" : "false",
    "native_address" : "0x195b42a24",
    "native_offset" : "0x00000"
  }
,
 {
    "is_managed" : "false",
    "native_address" : "0x19596499c",
    "native_offset" : "0x00000"
  }
,
 {
    "is_managed" : "false",
    "native_address" : "0x195965050",
    "native_offset" : "0x00000"
  }
,
 {
    "is_managed" : "false",
    "native_address" : "0x107a902a4",
    "native_offset" : "0x00000"
  }
,
 {
    "is_managed" : "false",
    "native_address" : "0x1057a0d58",
    "native_offset" : "0x00000"
  }
,
 {
    "is_managed" : "false",
    "native_address" : "0x1057a1f3c",
    "native_offset" : "0x00000"
  }
,
 {
    "is_managed" : "false",
    "native_address" : "0x105a017d8",
    "native_offset" : "0x00000"
  }
,
 {
    "is_managed" : "false",
    "native_address" : "0x195b13fa8",
    "native_offset" : "0x00000"
  }
,
 {
    "is_managed" : "false",
    "native_address" : "0x195b0eda0",
    "native_offset" : "0x00000"
  }

 ]
},
{
  "is_managed" : true,
  "offset_free_hash" : "0x1224727402",
  "offset_rich_hash" : "0x12247275cb",
  "crashed" : false,
  "native_thread_id" : "0x2adf9b000",
  "thread_info_addr" : "0x2bf4e2800",
  "thread_name" : "Timer-Scheduler",
  "ctx" : {
    "IP" : "0x195ad7710",
    "SP" : "0x2adf99ec0",
    "BP" : "0x2adf99f50"
 },
  "managed_frames" : [
 {
    "is_managed" : "false",
    "native_address" : "unregistered"
  }
,
 {
    "is_managed" : "true",
    "guid" : "8F2B770C-4A1B-401A-99BA-9ED80A5C09B9",
    "token" : "0x00000",
    "native_offset" : "0x0",
    "filename" : "mscorlib.dll",
    "sizeofimage" : "0x470000",
    "timestamp" : "0xa6d36809",
    "il_offset" : "0xffffffff"
  }
,
 {
    "is_managed" : "true",
    "guid" : "8F2B770C-4A1B-401A-99BA-9ED80A5C09B9",
    "token" : "0x60020b2",
    "native_offset" : "0x0",
    "filename" : "mscorlib.dll",
    "sizeofimage" : "0x470000",
    "timestamp" : "0xa6d36809",
    "il_offset" : "0x00044"
  }
,
 {
    "is_managed" : "true",
    "guid" : "8F2B770C-4A1B-401A-99BA-9ED80A5C09B9",
    "token" : "0x600209e",
    "native_offset" : "0x0",
    "filename" : "mscorlib.dll",
    "sizeofimage" : "0x470000",
    "timestamp" : "0xa6d36809",
    "il_offset" : "0x00014"
  }
,
 {
    "is_managed" : "true",
    "guid" : "8F2B770C-4A1B-401A-99BA-9ED80A5C09B9",
    "token" : "0x600209d",
    "native_offset" : "0x0",
    "filename" : "mscorlib.dll",
    "sizeofimage" : "0x470000",
    "timestamp" : "0xa6d36809",
    "il_offset" : "0x00000"
  }
,
 {
    "is_managed" : "true",
    "guid" : "8F2B770C-4A1B-401A-99BA-9ED80A5C09B9",
    "token" : "0x6002098",
    "native_offset" : "0x0",
    "filename" : "mscorlib.dll",
    "sizeofimage" : "0x470000",
    "timestamp" : "0xa6d36809",
    "il_offset" : "0x00019"
  }
,
 {
    "is_managed" : "true",
    "guid" : "8F2B770C-4A1B-401A-99BA-9ED80A5C09B9",
    "token" : "0x600209b",
    "native_offset" : "0x0",
    "filename" : "mscorlib.dll",
    "sizeofimage" : "0x470000",
    "timestamp" : "0xa6d36809",
    "il_offset" : "0x00000"
  }
,
 {
    "is_managed" : "true",
    "guid" : "8F2B770C-4A1B-401A-99BA-9ED80A5C09B9",
    "token" : "0x600215a",
    "native_offset" : "0x0",
    "filename" : "mscorlib.dll",
    "sizeofimage" : "0x470000",
    "timestamp" : "0xa6d36809",
    "il_offset" : "0x0003c"
  }
,
 {
    "is_managed" : "true",
    "guid" : "8F2B770C-4A1B-401A-99BA-9ED80A5C09B9",
    "token" : "0x6001f7d",
    "native_offset" : "0x0",
    "filename" : "mscorlib.dll",
    "sizeofimage" : "0x470000",
    "timestamp" : "0xa6d36809",
    "il_offset" : "0x00014"
  }
,
 {
    "is_managed" : "true",
    "guid" : "8F2B770C-4A1B-401A-99BA-9ED80A5C09B9",
    "token" : "0x6001f25",
    "native_offset" : "0x0",
    "filename" : "mscorlib.dll",
    "sizeofimage" : "0x470000",
    "timestamp" : "0xa6d36809",
    "il_offset" : "0x00071"
  }
,
 {
    "is_managed" : "true",
    "guid" : "8F2B770C-4A1B-401A-99BA-9ED80A5C09B9",
    "token" : "0x6001f23",
    "native_offset" : "0x0",
    "filename" : "mscorlib.dll",
    "sizeofimage" : "0x470000",
    "timestamp" : "0xa6d36809",
    "il_offset" : "0x00000"
  }
,
 {
    "is_managed" : "true",
    "guid" : "8F2B770C-4A1B-401A-99BA-9ED80A5C09B9",
    "token" : "0x6001f22",
    "native_offset" : "0x0",
    "filename" : "mscorlib.dll",
    "sizeofimage" : "0x470000",
    "timestamp" : "0xa6d36809",
    "il_offset" : "0x0002b"
  }
,
 {
    "is_managed" : "true",
    "guid" : "8F2B770C-4A1B-401A-99BA-9ED80A5C09B9",
    "token" : "0x6001f7f",
    "native_offset" : "0x0",
    "filename" : "mscorlib.dll",
    "sizeofimage" : "0x470000",
    "timestamp" : "0xa6d36809",
    "il_offset" : "0x00008"
  }
,
 {
    "is_managed" : "true",
    "guid" : "8F2B770C-4A1B-401A-99BA-9ED80A5C09B9",
    "token" : "0x00000",
    "native_offset" : "0x0",
    "filename" : "mscorlib.dll",
    "sizeofimage" : "0x470000",
    "timestamp" : "0xa6d36809",
    "il_offset" : "0x00065"
  }

 ],
"unmanaged_frames" : [
{
  "is_managed" : "false",
  "native_address" : "0x298a055f8",
  "native_offset" : "0x00000"
 }
,
{
  "is_managed" : "false",
  "native_address" : "0x298b3c6b8",
  "native_offset" : "0x00000"
 }
,
{
  "is_managed" : "false",
  "native_address" : "0x298b3ca14",
  "native_offset" : "0x00000"
 }
,
{
  "is_managed" : "false",
  "native_address" : "0x298b3c7dc",
  "native_offset" : "0x00000"
 }
,
{
  "is_managed" : "false",
  "native_address" : "0x298a4660c",
  "native_offset" : "0x00000"
 }
,
{
  "is_managed" : "false",
  "native_address" : "0x195b42a24",
  "native_offset" : "0x00000"
 }
,
{
  "is_managed" : "false",
  "native_address" : "0x195b14574",
  "native_offset" : "0x00000"
 }
,
{
  "is_managed" : "false",
  "native_address" : "0x298b8be94",
  "native_offset" : "0x00000"
 }
,
{
  "is_managed" : "false",
  "native_address" : "0x298b483e8",
  "native_offset" : "0x00000"
 }
,
{
  "is_managed" : "false",
  "native_address" : "0x298b4821c",
  "native_offset" : "0x00000"
 }
,
{
  "is_managed" : "false",
  "native_address" : "0x298b484b4",
  "native_offset" : "0x00000"
 }
,
{
  "is_managed" : "false",
  "native_address" : "0x298b37888",
  "native_offset" : "0x00000"
 }
,
{
  "is_managed" : "false",
  "native_address" : "0x298ae1fd4",
  "native_offset" : "0x00000"
 }
,
{
  "is_managed" : "true",
  "guid" : "8F2B770C-4A1B-401A-99BA-9ED80A5C09B9",
  "token" : "0x00000",
  "native_offset" : "0x0",
  "filename" : "mscorlib.dll",
  "sizeofimage" : "0x470000",
  "timestamp" : "0xa6d36809",
  "il_offset" : "0x00000"
 }
,
{
  "is_managed" : "true",
  "guid" : "8F2B770C-4A1B-401A-99BA-9ED80A5C09B9",
  "token" : "0x60020b2",
  "native_offset" : "0x0",
  "filename" : "mscorlib.dll",
  "sizeofimage" : "0x470000",
  "timestamp" : "0xa6d36809",
  "il_offset" : "0x00000"
 }
,
{
  "is_managed" : "true",
  "guid" : "8F2B770C-4A1B-401A-99BA-9ED80A5C09B9",
  "token" : "0x600209e",
  "native_offset" : "0x0",
  "filename" : "mscorlib.dll",
  "sizeofimage" : "0x470000",
  "timestamp" : "0xa6d36809",
  "il_offset" : "0x00000"
 }
,
{
  "is_managed" : "true",
  "guid" : "8F2B770C-4A1B-401A-99BA-9ED80A5C09B9",
  "token" : "0x600209d",
  "native_offset" : "0x0",
  "filename" : "mscorlib.dll",
  "sizeofimage" : "0x470000",
  "timestamp" : "0xa6d36809",
  "il_offset" : "0x00000"
 }
,
{
  "is_managed" : "true",
  "guid" : "8F2B770C-4A1B-401A-99BA-9ED80A5C09B9",
  "token" : "0x6002098",
  "native_offset" : "0x0",
  "filename" : "mscorlib.dll",
  "sizeofimage" : "0x470000",
  "timestamp" : "0xa6d36809",
  "il_offset" : "0x00000"
 }
,
{
  "is_managed" : "true",
  "guid" : "8F2B770C-4A1B-401A-99BA-9ED80A5C09B9",
  "token" : "0x600209b",
  "native_offset" : "0x0",
  "filename" : "mscorlib.dll",
  "sizeofimage" : "0x470000",
  "timestamp" : "0xa6d36809",
  "il_offset" : "0x00000"
 }
,
{
  "is_managed" : "true",
  "guid" : "8F2B770C-4A1B-401A-99BA-9ED80A5C09B9",
  "token" : "0x600215a",
  "native_offset" : "0x0",
  "filename" : "mscorlib.dll",
  "sizeofimage" : "0x470000",
  "timestamp" : "0xa6d36809",
  "il_offset" : "0x00000"
 }
,
{
  "is_managed" : "true",
  "guid" : "8F2B770C-4A1B-401A-99BA-9ED80A5C09B9",
  "token" : "0x6001f7d",
  "native_offset" : "0x0",
  "filename" : "mscorlib.dll",
  "sizeofimage" : "0x470000",
  "timestamp" : "0xa6d36809",
  "il_offset" : "0x00000"
 }
,
{
  "is_managed" : "true",
  "guid" : "8F2B770C-4A1B-401A-99BA-9ED80A5C09B9",
  "token" : "0x6001f25",
  "native_offset" : "0x0",
  "filename" : "mscorlib.dll",
  "sizeofimage" : "0x470000",
  "timestamp" : "0xa6d36809",
  "il_offset" : "0x00000"
 }
,
{
  "is_managed" : "true",
  "guid" : "8F2B770C-4A1B-401A-99BA-9ED80A5C09B9",
  "token" : "0x6001f23",
  "native_offset" : "0x0",
  "filename" : "mscorlib.dll",
  "sizeofimage" : "0x470000",
  "timestamp" : "0xa6d36809",
  "il_offset" : "0x00000"
 }
,
{
  "is_managed" : "true",
  "guid" : "8F2B770C-4A1B-401A-99BA-9ED80A5C09B9",
  "token" : "0x6001f22",
  "native_offset" : "0x0",
  "filename" : "mscorlib.dll",
  "sizeofimage" : "0x470000",
  "timestamp" : "0xa6d36809",
  "il_offset" : "0x00000"
 }
,
{
  "is_managed" : "true",
  "guid" : "8F2B770C-4A1B-401A-99BA-9ED80A5C09B9",
  "token" : "0x6001f7f",
  "native_offset" : "0x0",
  "filename" : "mscorlib.dll",
  "sizeofimage" : "0x470000",
  "timestamp" : "0xa6d36809",
  "il_offset" : "0x00000"
 }
,
{
  "is_managed" : "true",
  "guid" : "8F2B770C-4A1B-401A-99BA-9ED80A5C09B9",
  "token" : "0x00000",
  "native_offset" : "0x0",
  "filename" : "mscorlib.dll",
  "sizeofimage" : "0x470000",
  "timestamp" : "0xa6d36809",
  "il_offset" : "0x00000"
 }
,
{
  "is_managed" : "false",
  "native_address" : "0x298995178",
  "native_offset" : "0x00000"
 }
,
{
  "is_managed" : "false",
  "native_address" : "0x298b1b3ec",
  "native_offset" : "0x00000"
 }
,
{
  "is_managed" : "false",
  "native_address" : "0x298b1cffc",
  "native_offset" : "0x00000"
 }
,
{
  "is_managed" : "false",
  "native_address" : "0x298b3d518",
  "native_offset" : "0x00000"
 }
,
{
  "is_managed" : "false",
  "native_address" : "0x298b3d2d0",
  "native_offset" : "0x00000"
 }
,
{
  "is_managed" : "false",
  "native_address" : "0x298bbcd18",
  "native_offset" : "0x00000"
 }
,
{
  "is_managed" : "false",
  "native_address" : "0x298bbcca0",
  "native_offset" : "0x00000"
 }
,
{
  "is_managed" : "false",
  "native_address" : "0x195b13fa8",
  "native_offset" : "0x00000"
 }
,
{
  "is_managed" : "false",
  "native_address" : "0x195b0eda0",
  "native_offset" : "0x00000"
 }

]
},
{
"is_managed" : false,
"offset_free_hash" : "0x0",
"offset_rich_hash" : "0x0",
"crashed" : false,
"native_thread_id" : "0x298973000",
"thread_info_addr" : "0x126163c00",
"thread_name" : "Debugger agent",
"ctx" : {
  "IP" : "0x195adc808",
  "SP" : "0x298972aa0",
  "BP" : "0x298972ae0"
},
"unmanaged_frames" : [
{
  "is_managed" : "false",
  "native_address" : "0x298a055f8",
  "native_offset" : "0x00000"
 }
,
{
  "is_managed" : "false",
  "native_address" : "0x298b3c6b8",
  "native_offset" : "0x00000"
 }
,
{
  "is_managed" : "false",
  "native_address" : "0x298b3ca14",
  "native_offset" : "0x00000"
 }
,
{
  "is_managed" : "false",
  "native_address" : "0x298b3c7dc",
  "native_offset" : "0x00000"
 }
,
{
  "is_managed" : "false",
  "native_address" : "0x298a4660c",
  "native_offset" : "0x00000"
 }
,
{
  "is_managed" : "false",
  "native_address" : "0x195b42a24",
  "native_offset" : "0x00000"
 }
,
{
  "is_managed" : "false",
  "native_address" : "0x298a757c8",
  "native_offset" : "0x00000"
 }
,
{
  "is_managed" : "false",
  "native_address" : "0x298a6c3c4",
  "native_offset" : "0x00000"
 }
,
{
  "is_managed" : "false",
  "native_address" : "0x298b3d424",
  "native_offset" : "0x00000"
 }
,
{
  "is_managed" : "false",
  "native_address" : "0x298b3d2d0",
  "native_offset" : "0x00000"
 }
,
{
  "is_managed" : "false",
  "native_address" : "0x298bbcd18",
  "native_offset" : "0x00000"
 }
,
{
  "is_managed" : "false",
  "native_address" : "0x298bbcca0",
  "native_offset" : "0x00000"
 }
,
{
  "is_managed" : "false",
  "native_address" : "0x195b13fa8",
  "native_offset" : "0x00000"
 }
,
{
  "is_managed" : "false",
  "native_address" : "0x195b0eda0",
  "native_offset" : "0x00000"
 }

]
},
{
"is_managed" : false,
"offset_free_hash" : "0x0",
"offset_rich_hash" : "0x0",
"crashed" : false,
"native_thread_id" : "0x2a0137000",
"thread_info_addr" : "0x12426ec00",
"thread_name" : "tid_30dab",
"ctx" : {
  "IP" : "0x195ad3e90",
  "SP" : "0x2a0136dd0",
  "BP" : "0x2a0136de0"
},
"unmanaged_frames" : [
{
  "is_managed" : "false",
  "native_address" : "0x298a055f8",
  "native_offset" : "0x00000"
 }
,
{
  "is_managed" : "false",
  "native_address" : "0x298b3c6b8",
  "native_offset" : "0x00000"
 }
,
{
  "is_managed" : "false",
  "native_address" : "0x298b3ca14",
  "native_offset" : "0x00000"
 }
,
{
  "is_managed" : "false",
  "native_address" : "0x298b3c7dc",
  "native_offset" : "0x00000"
 }
,
{
  "is_managed" : "false",
  "native_address" : "0x298a4660c",
  "native_offset" : "0x00000"
 }
,
{
  "is_managed" : "false",
  "native_address" : "0x195b42a24",
  "native_offset" : "0x00000"
 }
,
{
  "is_managed" : "false",
  "native_address" : "0x19596499c",
  "native_offset" : "0x00000"
 }
,
{
  "is_managed" : "false",
  "native_address" : "0x195965050",
  "native_offset" : "0x00000"
 }
,
{
  "is_managed" : "false",
  "native_address" : "0x107a902a4",
  "native_offset" : "0x00000"
 }
,
{
  "is_managed" : "false",
  "native_address" : "0x105460d74",
  "native_offset" : "0x00000"
 }
,
{
  "is_managed" : "false",
  "native_address" : "0x105853ebc",
  "native_offset" : "0x00000"
 }
,
{
  "is_managed" : "false",
  "native_address" : "0x105853e58",
  "native_offset" : "0x00000"
 }
,
{
  "is_managed" : "false",
  "native_address" : "0x105a017d8",
  "native_offset" : "0x00000"
 }
,
{
  "is_managed" : "false",
  "native_address" : "0x195b13fa8",
  "native_offset" : "0x00000"
 }
,
{
  "is_managed" : "false",
  "native_address" : "0x195b0eda0",
  "native_offset" : "0x00000"
 }

]
}
]
}